{
  "version": "0.3.4",
  "buildTime": "2026-04-22 21:11 CEST",
  "buildNote": {
    "zh": "官网升级 · 双语切换 · 品牌焕新",
    "en": "Website refresh · bilingual switch · brand update"
  },
  "appSize": "pending validation",
  "downloadFile": "GitHub project",
  "downloadPath": "https://github.com/HiClawBot/Sleeepal",
  "downloadSize": "85M",
  "downloadSub": {
    "zh": "官网升级版已公开 · App 产物将在验证完成后单独发布",
    "en": "The refreshed website is now public · app builds will be released separately after validation"
  },
  "downloadButton": {
    "zh": "查看 GitHub 项目",
    "en": "View GitHub project"
  },
  "sysreq": {
    "zh": "官网已上线 · 二进制产物后续发布",
    "en": "Website is live · binaries will follow later"
  },
  "releaseLabel": {
    "zh": "当前构建",
    "en": "Current build"
  },
  "packagedLabel": {
    "zh": "打包时间",
    "en": "Packaged"
  },
  "progress": {
    "zh": [
      "官网风格升级，品牌图标更新为金色月牙 + 深蓝色 zzz。",
      "新增中英文切换脚手架，先覆盖核心公开页面文案。",
      "应用端 UI 统一、全量双语和正式产物发布继续在验证链路中。"
    ],
    "en": [
      "The site has been refreshed with the new gold crescent and deep-blue zzz brand mark.",
      "A bilingual switch now covers the core public-facing content in Chinese and English.",
      "App UI alignment, full bilingual product surfaces, and public binaries remain in active validation."
    ]
  }
}
